kedro_azureml/__init__.py
kedro_azureml/auth/__init__.py
kedro_azureml/auth/utils.py
kedro_azureml/cli.py
kedro_azureml/cli_functions.py
kedro_azureml/client.py
kedro_azureml/config.py
kedro_azureml/constants.py
kedro_azureml/datasets/__init__.py
kedro_azureml/datasets/asset_dataset.py
kedro_azureml/datasets/file_dataset.py
kedro_azureml/datasets/pandas_dataset.py
kedro_azureml/datasets/pipeline_dataset.py
kedro_azureml/datasets/runner_dataset.py
kedro_azureml/datasets/v1_datasets.py
kedro_azureml/distributed/__init__.py
kedro_azureml/distributed/config.py
kedro_azureml/distributed/decorators.py
kedro_azureml/distributed/utils.py
kedro_azureml/generator.py
kedro_azureml/hooks.py
kedro_azureml/manager.py
kedro_azureml/runner.py
kedro_azureml/utils.py
kedro_azureml-1.0.0.dist-info/LICENSE
kedro_azureml-1.0.0.dist-info/METADATA
kedro_azureml-1.0.0.dist-info/WHEEL
kedro_azureml-1.0.0.dist-info/entry_points.txt
kedro_azureml-1.0.0.dist-info/RECORD
