Metadata-Version: 2.3
Name: kedro-azureml
Version: 1.0.0
Summary: Kedro plugin with Azure ML Pipelines support
License: Apache-2.0
Keywords: kedro,mlops,azureml,machinelearning
Author: marcin.zablocki
Author-email: marcin.zablocki@getindata.com
Maintainer: GetInData MLOPS
Maintainer-email: mlops@getindata.com
Requires-Python: >=3.9,<3.13
Classifier: Development Status :: 4 - Beta
Classifier: License :: OSI Approved :: Apache Software License
Classifier: Programming Language :: Python :: 3
Classifier: Programming Language :: Python :: 3.9
Classifier: Programming Language :: Python :: 3.10
Classifier: Programming Language :: Python :: 3.11
Classifier: Programming Language :: Python :: 3.12
Provides-Extra: mlflow
Requires-Dist: adlfs (>=2022.2.0)
Requires-Dist: azure-ai-ml (>=1.2.0)
Requires-Dist: azureml-mlflow (>=1.42.0) ; extra == "mlflow"
Requires-Dist: backoff (>=2.2.1,<3.0.0)
Requires-Dist: cloudpickle (>=2.1.0,<3.0.0)
Requires-Dist: kedro (>=1.0.0,<2.0.0)
Requires-Dist: kedro-datasets (>=1.0.0)
Requires-Dist: mlflow (>2.0.0,<3.0.0) ; extra == "mlflow"
Requires-Dist: pyarrow (>=11.0.0)
Requires-Dist: pydantic (>=2.6.4,<2.11.0)
Project-URL: Documentation, https://kedro-azureml.readthedocs.io/
Project-URL: Homepage, https://github.com/getindata/kedro-azureml
Project-URL: Repository, https://github.com/getindata/kedro-azureml
